liccheck/__init__.py
liccheck/__main__.py
liccheck/command_line.py
liccheck/requirements.py
liccheck-0.9.2.dist-info/LICENSE
liccheck-0.9.2.dist-info/METADATA
liccheck-0.9.2.dist-info/WHEEL
liccheck-0.9.2.dist-info/entry_points.txt
liccheck-0.9.2.dist-info/top_level.txt
liccheck-0.9.2.dist-info/RECORD
