Metadata-Version: 2.1
Name: liccheck
Version: 0.9.2
Summary: Check python packages from requirement.txt and report issues
Home-page: https://github.com/dhatim/python-license-check
Author: Dhatim
Author-email: contact@dhatim.com
License: Apache Software License
Keywords: license check build tool
Platform: UNKNOWN
Classifier: Development Status :: 5 - Production/Stable
Classifier: Intended Audience :: Developers
Classifier: Topic :: Software Development :: Build Tools
Classifier: License :: OSI Approved :: Apache Software License
Classifier: Programming Language :: Python :: 3
Classifier: Programming Language :: Python :: 3.5
Classifier: Programming Language :: Python :: 3.6
Classifier: Programming Language :: Python :: 3.7
Classifier: Programming Language :: Python :: 3.8
Requires-Python: >=3.5
License-File: LICENSE
